usepolvo/brain/__init__.py
usepolvo/brain/base.py
usepolvo/brain/config.py
usepolvo/brain/cortex.py
usepolvo/brain/memory.py
usepolvo/brain/synapse.py
usepolvo/brain/utils.py
usepolvo/core/config.py
usepolvo/core/exceptions.py
usepolvo/core/auth/__init__.py
usepolvo/core/auth/api_key.py
usepolvo/core/auth/base.py
usepolvo/core/auth/jwt.py
usepolvo/core/auth/multi_user.py
usepolvo/core/auth/oauth2.py
usepolvo/core/auth/tokens.py
usepolvo/core/clients/__init__.py
usepolvo/core/clients/base.py
usepolvo/core/clients/graphql.py
usepolvo/core/clients/rest.py
usepolvo/core/clients/user_context.py
usepolvo/core/rate_limiters/__init__.py
usepolvo/core/rate_limiters/adaptive.py
usepolvo/core/rate_limiters/base.py
usepolvo/core/rate_limiters/bucketed.py
usepolvo/core/rate_limiters/multi_window.py
usepolvo/core/rate_limiters/simple.py
usepolvo/core/tools/__init__.py
usepolvo/core/tools/api.py
usepolvo/core/tools/base.py
usepolvo/core/tools/registry.py
usepolvo/core/webhooks/__init__.py
usepolvo/core/webhooks/base.py
usepolvo/core/webhooks/server.py
usepolvo/core/webhooks/validators.py
usepolvo/tentacles/__init__.py
usepolvo/tentacles/base.py
usepolvo/tentacles/anthropic/__init__.py
usepolvo/tentacles/anthropic/client.py
usepolvo/tentacles/anthropic/config.py
usepolvo/tentacles/anthropic/messages.py
usepolvo/tentacles/gemini/__init__.py
usepolvo/tentacles/gemini/client.py
usepolvo/tentacles/gemini/config.py
usepolvo/tentacles/gemini/embeddings.py
usepolvo/tentacles/gemini/generation.py
usepolvo/tentacles/google_drive/__init__.py
usepolvo/tentacles/google_drive/client.py
usepolvo/tentacles/google_drive/config.py
usepolvo/tentacles/google_drive/files.py
usepolvo/tentacles/hubspot/__init__.py
usepolvo/tentacles/hubspot/client.py
usepolvo/tentacles/hubspot/companies.py
usepolvo/tentacles/hubspot/config.py
usepolvo/tentacles/hubspot/contacts.py
usepolvo/tentacles/hubspot/deals.py
usepolvo/tentacles/hubspot/models.py
usepolvo/tentacles/openai/__init__.py
usepolvo-1.1.6.dist-info/METADATA
usepolvo-1.1.6.dist-info/WHEEL
usepolvo-1.1.6.dist-info/top_level.txt
usepolvo-1.1.6.dist-info/RECORD
