Metadata-Version: 2.4
Name: usepolvo
Version: 1.1.6
Summary: A comprehensive integration package supporting various services.
Author-email: Caio Pizzol <hi@usepolvo.com>
License-Expression: MIT
Requires-Python: >=3.10
Requires-Dist: aiohttp~=3.11
Requires-Dist: asyncio~=3.4
Requires-Dist: cryptography~=44.0
Requires-Dist: gql~=3.5
Requires-Dist: pydantic-settings~=2.8
Requires-Dist: pydantic[email]~=2.11
Requires-Dist: python-dotenv~=1.1
Requires-Dist: ratelimit~=2.2
Requires-Dist: requests~=2.32
Requires-Dist: tenacity~=9.1
Provides-Extra: hubspot
Requires-Dist: hubspot-api-client~=11.1; extra == "hubspot"
Provides-Extra: gemini
Requires-Dist: google-genai~=1.9; extra == "gemini"
Provides-Extra: openai
Requires-Dist: openai~=1.70; extra == "openai"
Provides-Extra: anthropic
Requires-Dist: anthropic~=0.49; extra == "anthropic"
Provides-Extra: google-drive
Requires-Dist: google-api-python-client~=2.166; extra == "google-drive"
Requires-Dist: google-auth-httplib2~=0.2; extra == "google-drive"
Requires-Dist: google-auth-oauthlib~=1.2; extra == "google-drive"
Provides-Extra: all
Requires-Dist: hubspot-api-client~=11.1; extra == "all"
Requires-Dist: google-genai~=1.9; extra == "all"
Requires-Dist: openai~=1.70; extra == "all"
Requires-Dist: anthropic~=0.49; extra == "all"
Requires-Dist: google-api-python-client~=2.166; extra == "all"
Requires-Dist: google-auth-httplib2~=0.2; extra == "all"
Requires-Dist: google-auth-oauthlib~=1.2; extra == "all"
